ptvis_app/__init__.py
ptvis_app/__main__.py
ptvis_app/_version.py
ptvis_app/application.py
ptvis_app/command.py
ptvis_app/exceptions.py
ptvis_app/logging.py
ptvis_app/periodic_table.py
ptvis_app/py.typed
ptvis_app/utils.py
ptvis_app/widgets.py
ptvis_app/static/favicon.svg
ptvis_app-1.0.0.dist-info/licenses/LICENSE.txt
ptvis_app-1.0.0.dist-info/METADATA
ptvis_app-1.0.0.dist-info/WHEEL
ptvis_app-1.0.0.dist-info/entry_points.txt
ptvis_app-1.0.0.dist-info/top_level.txt
ptvis_app-1.0.0.dist-info/RECORD
