Metadata-Version: 2.4
Name: ptvis-app
Version: 1.0.0
Summary: GUI application for visualizing data on the periodic table
Home-page: https://gitlab.com/naubuan/ptvis-app/
Author: naubuan
License: Apache License 2.0
Classifier: License :: OSI Approved :: Apache Software License
Classifier: Programming Language :: Python :: 3.10
Classifier: Programming Language :: Python :: 3.11
Classifier: Programming Language :: Python :: 3.12
Classifier: Programming Language :: Python :: 3.13
Classifier: Topic :: Scientific/Engineering :: Chemistry
Classifier: Topic :: Scientific/Engineering :: Visualization
Requires-Python: >=3.10
License-File: LICENSE.txt
Requires-Dist: colorcet>=3.0.1
Requires-Dist: kaleido
Requires-Dist: pandas>=2.0.0
Requires-Dist: panel>=1.5.4
Requires-Dist: param>=2.1.0
Requires-Dist: plotly>=5.12.0
Requires-Dist: ptvis>=2.0.0
Requires-Dist: python-dateutil>=2.9.0
Requires-Dist: wclr
Dynamic: license-file
